pynaompc/__init__.py
pynaompc/pynaompc.py
pynaompc/pynaompc.pyi
naompc-0.0.1.dist-info/METADATA
naompc-0.0.1.dist-info/WHEEL
naompc-0.0.1.dist-info/top_level.txt
naompc-0.0.1.dist-info/RECORD
