Metadata-Version: 2.1
Name: naompc
Version: 0.0.1
Summary: Cose
Author: Davide Ceriola, Flavio Maiorana, Luca Murra
Author-email: boh@gmail.com
Requires-Python: >=3.7
Provides-Extra: test
Requires-Dist: pytest>=6.0; extra == "test"
